{"filename": "Discotech_VIP_bottle_service_guestlists_tickets_v3.9.0_apkpure.com.apk", "appID": "me.discotech", "permissions": ["android.permission.WAKE_LOCK", "android.permission.INTERNET", "com.google.android.c2dm.permission.RECEIVE", "android.permission.READ_CONTACTS", "android.permission.WRITE_EXTERNAL_STORAGE", "android.permission.READ_EXTERNAL_STORAGE", "android.permission.VIBRATE", "android.permission.ACCESS_FINE_LOCATION", "android.permission.ACCESS_NETWORK_STATE", "com.google.android.providers.gsf.permission.READ_GSERVICES", "com.google.android.finsky.permission.BIND_GET_INSTALL_REFERRER_SERVICE"], "libraries": [], "time": 1224.5369999408722}