{"filename": "My_Pregnancy_Calculator_v1.0.0_apkpure.com.apk", "appID": "com.ecare.pregnancycalculator2", "permissions": ["android.permission.INTERNET", "android.permission.WRITE_EXTERNAL_STORAGE", "android.permission.ACCESS_NETWORK_STATE", "android.permission.READ_EXTERNAL_STORAGE", "android.permission.WAKE_LOCK"], "libraries": [{"name": "okhttp-3.10.0", "version": [""], "category": "libs", "root_package_exist": true, "similarity": 0.8360655737704918, "matched_root_package": ["Lokhttp3"], "shrink_percentage": 1}], "time": 74.82999992370605}