{"filename": "dasho-com.claha.showtimeremote.apk", "appID": "com.claha.showtimeremote", "permissions": ["android.permission.INTERNET"], "libraries": [{"name": "halfnarp-client-2.0.0", "version": [""], "category": "libs", "root_package_exist": false, "similarity": 1.0, "matched_root_package": ["Landroid/support/v7/appcompat"], "shrink_percentage": 0.10714285714285714}, {"name": "jsr305-2.0.1", "version": [""], "category": "libs", "root_package_exist": false, "similarity": 0.2, "matched_root_package": ["Lcom/claha/showtimeremote"], "shrink_percentage": 1}, {"name": "com.github.bumptech.glide.okhttp-integration.1.4.0", "version": [""], "category": "libs", "root_package_exist": false, "similarity": 0.2, "matched_root_package": ["Lcom/claha/showtimeremote"], "shrink_percentage": 1}, {"name": "junidecode-v0.2", "version": [""], "category": "libs", "root_package_exist": false, "similarity": 0.01098901098901099, "matched_root_package": ["Lcom/claha/showtimeremote"], "shrink_percentage": 1}, {"name": "jsr305-3.0.0", "version": [""], "category": "libs", "root_package_exist": false, "similarity": 0.2, "matched_root_package": ["Lcom/claha/showtimeremote"], "shrink_percentage": 1}], "time": 9.77999997138977}