{"filename": "BeatSync_Hot_Videos_Easy_Quick_v4.0.146_apkpure.com.apk", "appID": "com.kinemaster.app.beatsync", "permissions": ["android.permission.INTERNET", "android.permission.ACCESS_NETWORK_STATE", "android.permission.ACCESS_WIFI_STATE", "android.permission.READ_PHONE_STATE", "android.permission.READ_EXTERNAL_STORAGE", "android.permission.WRITE_EXTERNAL_STORAGE", "android.permission.PACKAGE_USAGE_STATS", "android.permission.QUERY_ALL_PACKAGES", "android.permission.WAKE_LOCK", "android.permission.RECEIVE_BOOT_COMPLETED", "com.google.android.finsky.permission.BIND_GET_INSTALL_REFERRER_SERVICE", "android.permission.FOREGROUND_SERVICE"], "libraries": [], "time": 1109.62299990654}