{"filename": "Photo_Collage_Maker_Photo_Editor_v1.142.17_apkpure.com.apk", "appID": "photocollage.photoeditor.photocollageeditor", "permissions": ["android.permission.WRITE_EXTERNAL_STORAGE", "android.permission.INTERNET", "android.permission.ACCESS_NETWORK_STATE", "com.google.android.gallery3d.permission.GALLERY_PROVIDER", "com.google.android.apps.photos.permission.GOOGLE_PHOTOS", "com.google.android.providers.gsf.permission.READ_GSERVICES", "com.android.vending.BILLING", "android.permission.READ_EXTERNAL_STORAGE", "android.permission.WAKE_LOCK", "com.google.android.finsky.permission.BIND_GET_INSTALL_REFERRER_SERVICE", "com.google.android.c2dm.permission.RECEIVE", "photocollage.photoeditor.photocollageeditor.permission.C2D_MESSAGE"], "libraries": [], "time": 104.68799996376038}